YizhanshiXuexiWireshark/README.md
YizhanshiXuexiWireshark/__init__.py
YizhanshiXuexiWireshark/__main__.py
YizhanshiXuexiWireshark/file.epub
YizhanshiXuexiWireshark/index.html
YizhanshiXuexiWireshark/css/__init__.py
YizhanshiXuexiWireshark/css/annotations.css
YizhanshiXuexiWireshark/css/main.css
YizhanshiXuexiWireshark/css/normalize.css
YizhanshiXuexiWireshark/css/popup.css
YizhanshiXuexiWireshark/font/__init__.py
YizhanshiXuexiWireshark/font/fontello.eot
YizhanshiXuexiWireshark/font/fontello.svg
YizhanshiXuexiWireshark/font/fontello.ttf
YizhanshiXuexiWireshark/font/fontello.woff
YizhanshiXuexiWireshark/img/__init__.py
YizhanshiXuexiWireshark/img/annotator-glyph-sprite.png
YizhanshiXuexiWireshark/img/annotator-icon-sprite.png
YizhanshiXuexiWireshark/img/apple-touch-icon.png
YizhanshiXuexiWireshark/img/cancelfullscreen.png
YizhanshiXuexiWireshark/img/close.png
YizhanshiXuexiWireshark/img/fullscreen.png
YizhanshiXuexiWireshark/img/loader.gif
YizhanshiXuexiWireshark/img/menu-icon.png
YizhanshiXuexiWireshark/img/save.png
YizhanshiXuexiWireshark/img/saved.png
YizhanshiXuexiWireshark/img/settings-s.png
YizhanshiXuexiWireshark/img/settings.png
YizhanshiXuexiWireshark/img/star.png
YizhanshiXuexiWireshark/js/__init__.py
YizhanshiXuexiWireshark/js/epub.js
YizhanshiXuexiWireshark/js/epub.min.js
YizhanshiXuexiWireshark/js/epub.min.map
YizhanshiXuexiWireshark/js/hooks.min.js
YizhanshiXuexiWireshark/js/hooks.min.map
YizhanshiXuexiWireshark/js/reader.js
YizhanshiXuexiWireshark/js/reader.js.map
YizhanshiXuexiWireshark/js/reader.min.js
YizhanshiXuexiWireshark/js/reader.min.map
YizhanshiXuexiWireshark/js/hooks/__init__.py
YizhanshiXuexiWireshark/js/hooks/extensions/__init__.py
YizhanshiXuexiWireshark/js/hooks/extensions/highlight.js
YizhanshiXuexiWireshark/js/libs/__init__.py
YizhanshiXuexiWireshark/js/libs/jquery.min.js
YizhanshiXuexiWireshark/js/libs/localforage.min.js
YizhanshiXuexiWireshark/js/libs/screenfull.js
YizhanshiXuexiWireshark/js/libs/screenfull.min.js
yizhanshi_xuexi_wireshark-2024.3.2.0.dist-info/METADATA
yizhanshi_xuexi_wireshark-2024.3.2.0.dist-info/WHEEL
yizhanshi_xuexi_wireshark-2024.3.2.0.dist-info/entry_points.txt
yizhanshi_xuexi_wireshark-2024.3.2.0.dist-info/top_level.txt
yizhanshi_xuexi_wireshark-2024.3.2.0.dist-info/RECORD
